LICENSE
MANIFEST.in
README.md
setup.py
pyencrypt/__main__.py
pyencrypt/cli.py
pyencrypt/decryptor.py
pyencrypt/encryptor.py
pyencrypt.egg-info/PKG-INFO
pyencrypt.egg-info/SOURCES.txt
pyencrypt.egg-info/dependency_links.txt
pyencrypt.egg-info/entry_points.txt
pyencrypt.egg-info/requires.txt
pyencrypt.egg-info/top_level.txt