Metadata-Version: 1.0
Name: pyencrypt
Version: 0.0.4
Summary: Simple file encryptor using python
Home-page: https://github.com/bakku/pyencrypt
Author: Christian Paling
Author-email: christian.paling@googlemail.com
License: GNU GENERAL PUBLIC LICENSE
